{
    "files": {
        "input": "datasets/font.txt"
    },
    "iterations": 1000,
    "learningRate": 0.005,
    "beta": 1,
    "error": 0.001,
    "momentum": true,
    "calculateMetrics": false,
    "plotLatent": false,
    "alpha": 0.8,
    "layers": [
        {
            "activation": "nonlinear",
            "perceptrons": 35
        },
        {
            "activation": "nonlinear",
            "perceptrons": 17
        },
        {
            "activation": "nonlinear",
            "perceptrons": 2
        },
        {
            "activation": "nonlinear",
            "perceptrons": 17
        },
        {
            "activation": "nonlinear",
            "perceptrons": 35
        }
    ]
}